LICENSE
README.md
setup.cfg
setup.py
oodf/__init__.py
oodf/__lib__.py
oodf/methods.py
oodf/tokens.py
oodf.egg-info/PKG-INFO
oodf.egg-info/SOURCES.txt
oodf.egg-info/dependency_links.txt
oodf.egg-info/not-zip-safe
oodf.egg-info/top_level.txt
oodf/core/__init__.py
oodf/core/lexer.py
oodf/core/transpiler.py
oodf/exceptions/__init__.py
oodf/exceptions/base.py
oodf/exceptions/parser.py
tests/__init__.py
tests/test_comments.py
tests/test_keynotes.py
tests/test_token_types.py
tests/utils.py