Metadata-Version: 2.1
Name: oodf
Version: 0.0.1.dev1
Summary: A library for interacting with oodf (object oriented data format/file) in python.
Home-page: https://oodf.arthurdw.com
Author: Arthurdw
Author-email: mail@arthurdw.com
License: MIT
Project-URL: Github, https://github.com/Arthurdw/oodf
Project-URL: PyPI, https://pypi.org/project/oodf/
Keywords: oodf,file,format
Platform: all
Classifier: Development Status :: 2 - Pre-Alpha
Classifier: Intended Audience :: Developers
Classifier: Topic :: Software Development :: Build Tools
Classifier: License :: OSI Approved :: MIT License
Classifier: Programming Language :: Python :: 3 :: Only
Classifier: Programming Language :: Python :: 3.8
Classifier: Programming Language :: Python :: 3.9
Classifier: Programming Language :: Python :: 3.10
Requires-Python: >=3.8
